<?xml version="1.0" encoding="UTF-8"?>
<!DOCTYPE document SYSTEM "avis2.dtd" [<!ENTITY % HTMLsymbol SYSTEM "xhtml-symbol.ent"> %HTMLsymbol; ]>
<document>
<header>
<attribute name="file" value="AP-20190805-gleder-seg-til-em-fe.xml"/>
<attribute name="url" value="http://www.aftenposten.no/sport/i/6jyQr8/Gleder-seg-til-EM-fest-i-Sandnes-med-et-sterkt_-norsk-lag" frk="114 17 12 689"/>
<attribute name="source" value="AP"/>
<attribute name="date" value="2019-08-05 10:44"/>
<attribute name="author" value="Egil Ø. Nærland"/>
<attribute name="gender" value="M"/>
<attribute name="class1" value="sport"/>
<attribute name="class2" value=""/>
<attribute name="language" value="nob"/>
</header>
<body>
<div type="title" level="1">Gleder seg til EM-fest i Sandnes med et sterkt, norsk lag</div>
<div type="ingress">I helgen løper Ingebrigtsen-brødrene EM for lag på hjemmebane i Sandnes. De har med seg et særdeles sterkt, norsk lag.</div>
<div type="author">Egil Ø. Nærland</div>
<div type="date">05.aug.2019 12:44</div>
<div type="caption"><p>FOTO: VEGARD WIVESTAD GRØTT / BILDBYRÅN NORWAY Kommende helg er det på med landslagets drakt og tre løp på hjemmebane for Ingebrigtsens. Jakob løper 1500 m, Filip 5000 m og Henrik 3000 m.</p></div>
<div type="text">
<p>Hamar: Jakob Ingebrigtsen, Karsten Warholm, Henrik Ingebrigtsen, Filip Ingebrigtsen, Sondre Guttormsen, Karoline Bjerkeli Grøvdal, Ola Stuenes Isene. De er mange flere, det er bare å glede seg.</p>
<p>– Jeg husker NM for to år siden og håper EM for lag blir en folkefest som den gangen, sier Jakob Ingebrigtsen.</p></div></body></document>
