<?xml version="1.0" encoding="UTF-8"?>
<!DOCTYPE document SYSTEM "avis2.dtd" [<!ENTITY % HTMLsymbol SYSTEM "xhtml-symbol.ent"> %HTMLsymbol; ]>
<document>
<header>
<attribute name="file" value="DB-20190129-utbryterklubben-som-.xml"/>
<attribute name="url" value="http://www.dagbladet.no/sport/utbryterklubben-som-ble-kritisert-av-ferguson/70703776" frk="57 0 0 353 %%"/>
<attribute name="source" value="DB"/>
<attribute name="date" value="2019-01-29 20:46"/>
<attribute name="author" value="Christian M. Hugsted (i England)"/>
<attribute name="gender" value="M"/>
<attribute name="class1" value="sport"/>
<attribute name="class2" value="fotball,manchester united,pluss,manchester,fc united,sport"/>
<attribute name="language" value="nob"/>
</header>
<body>
<div type="title" level="1">Utbryterklubben som ble kritisert av Ferguson</div>
<div type="ingress">Hva er det som får flere tusen til å følge FC United i engelsk syvende divisjon? Dagbladet besøkte klubben som er kritisert av Sir Alex Ferguson og mislikt av mange United-supportere.</div>
<div type="author">Christian M. Hugsted (I England)</div>
<div type="date">2019-01-29</div>
<div type="caption"><p>SUPPORTERE: Dave Riley (t.v.) og Don Hogg er på plass for å følge FC United. Foto: Christian M. Hugsted</p></div>
</body></document>
