<?xml version="1.0" encoding="UTF-8"?>
<!DOCTYPE document SYSTEM "avis2.dtd" [<!ENTITY % HTMLsymbol SYSTEM "xhtml-symbol.ent"> %HTMLsymbol; ]>
<document>
<header>
<attribute name="file" value="DB-20190320-mallorca-innforer-al.xml"/>
<attribute name="url" value="http://www.dagbladet.no/tema/mallorca-innforer-alkoholregler/70892180" frk="471 6 18 2970"/>
<attribute name="source" value="DB"/>
<attribute name="date" value="2019-03-20 04:21"/>
<attribute name="author" value="Frode Andresen"/>
<attribute name="gender" value="M"/>
<attribute name="class1" value="tema"/>
<attribute name="class2" value="tema,alkohol,mallorca,reise"/>
<attribute name="language" value="nob"/>
</header>
<body>
<div type="title" level="1">Mallorca innfører alkoholregler</div>
<div type="ingress">Bystyret i byen Palma på den populære ferieøya har sett seg lei på fulle turister som spyr, slåss og forsøpler gatene.</div>
<div type="author">Frode Andresen</div>
<div type="date">2019-03-20</div>
<div type="caption"><p>ALKOHOLREGLER: 1. april innføres det nye regler for alkoholdrikking i Mallorca. Foto: NTB Scanpix</p> <p>FATALT: Så langt i år har seks turister falt i døden i Mallorca. Tre av dødsfallene, uavhengig av hverandre, skjedde fra dette bygget i Magaluf. Video: Ingrid Cogorno / Dagbladet Les saken her: https://www.dagbladet.no/nyheter/seks-har-falt-i-doden-i-ferieparadiset-i-ar-tre-av-dem-fra-denne-bygningen/70052812</p> <p>ADVARER: Talsmannen for aktivistgruppa Tot Inclòs i Mallorca kommer med en klar beskjed til norske turister. Video: Ingrid Cogorno / Foto: Anita Arntzen Les hele saken her: https://goo.gl/yEVuTL</p></div>
<div type="text">
<p>I jakten på sol og øl går det over styr for mange turister, noe som har ført til at lokale myndigheter på Mallorca har vedtatt restriksjoner mot alkohol i fire utsatte områder i byen Palma og på stranda Playa de Palma.</p>
<p>Palma regnes som hovedstaden i den autonome regionen Balearene.</p>
<p>De nye restriksjonene vil tre i kraft 1. april, noe som tillater politiet å dele ut bøter på opptil 3000 euro dersom regelverket brytes, melder BBC.</p>
<p>Barer, klubber og restauranter kan også bøtelegges. De får ikke lov til å promotere alkoholdrikking i gatene, og på enkelte steder vil det også bli forbudt med «happyhours» og «to-for-en»-tilbud.</p></div>
<div type="title" level="3">Utsatte områder</div>
<div type="text">
<p>Talsperson for turismedepartementet på Balearene, Alecandra Wilms, forteller at det er særlig to områder hvor de opplever at overstadig beruselse er et problem - Playa de Palma og Magaluf.</p>
<p>De nye reglene vil imidlertid ikke gjelde sistnevnte sted.</p>
<p>- Lokalbefolkningen har kjempet for at noe skal bli gjort i flere år. Problemet er fulle turister som samler seg og slåss i gatene - lokale beboere våkner opp til spy, søppel og knuste glass, fortalte Wilms til BBC i fjor.</p></div>
<div type="title" level="3">Turisthat</div>
<div type="text">
<p>For 10 til 20 år siden så mange land på turisme som en vei ut av fattigdom, siden det generer inntekter. Men de siste åra har vi sett at lokalbefolkningen på flere steder har gått til aksjon mot masseturisme - særlig på Mallorca, Ibiza og i Barcelona.</p>
<p>For under ett år siden var lokale myndigheter på Balearene, øygruppa som Mallorca, Menorca, Formentera og Ibiza er en del av, såpass lei av turister som var fulle allerede da de ankom flyplassen, at det ble foreslått reguleringer i alkoholkonsum på fly.</p></div>
<div type="title" level="3">- Etterlater hjernen hjemme</div>
<div type="text">
<p>I den forbindelse fortalte førsteamanuensis ved Universitetet i Stavanger og turismeforsker, Åsa Grahn, til Dagbladet at at mange etterlater hjernen hjemme i jakten på sol og billig øl.</p>
<p>- Dette reagerer lokalbefolkningen sterkt på. Det er ikke normalt for dem at folk drikker dag ut og dag inn, og går naken i gatene, sa hun.</p>
<p>Hun mente at en holdningsendring må til.</p>
<p>- Det er vanskelig å få folk til å endre seg, men jo mer vi snakker om det og synliggjør utfordringene, jo mer sannsynlig er det at turister vil begynne å ta mer ansvar.</p></div></body></document>
