<?xml version="1.0" encoding="UTF-8"?>
<!DOCTYPE document SYSTEM "avis2.dtd" [<!ENTITY % HTMLsymbol SYSTEM "xhtml-symbol.ent"> %HTMLsymbol; ]>
<document>
<header>
<attribute name="file" value="DB-20191007-rankingbyks.xml"/>
<attribute name="url" value="http://www.dagbladet.no/sport/rankingbyks/71680140" frk="114 27 21 768"/>
<attribute name="source" value="DB"/>
<attribute name="date" value="2019-10-07 06:40"/>
<attribute name="author" value="NTB I"/>
<attribute name="gender" value="U"/>
<attribute name="class1" value="sport"/>
<attribute name="class2" value=""/>
<attribute name="language" value="nob"/>
</header>
<body>
<div type="title" level="1">Rankingbyks</div>
<div type="ingress">Golfproffene Kristoffer Ventura og Viktor Hovland avanserer på golfrankingen. Ventura rykker 19 plasseringer oppover, mens Hovland klatrer to plasser.</div>
<div type="author">NTB I</div>
<div type="date">2019-10-07</div>
<div type="caption"><p>GOLFTALENT: Viktor Hovland fortsetter å klatre på rankingen. Det samme gjør landsmann Kristoffer Ventura. Foto: NTB scanpix</p></div>
<div type="text">
<p>Viktor Hovland, som ikke spilte i helgen, rykker opp fra 93. til 91. plass. Kristoffer Ventura tok 18.-plass i helgens PGA-turnering i Las Vegas og bykser opp 19 plasser til plass nummer 144.</p>
<p>Listen toppes av amerikanske Brooks Koepka foran nordiren Rory McIlroy.</p>
<p>Ventura skal i aksjon på PGA-touren i Houston fra torsdag, mens Hovland skal delta i de to PGA-turneringene i Asia. Først i Jeju, Sør-Korea (17.-20. oktober) og så i Chiba, Japan (24.-27. oktober).</p></div></body></document>
