<?xml version="1.0" encoding="UTF-8"?>
<!DOCTYPE document SYSTEM "avis2.dtd" [<!ENTITY % HTMLsymbol SYSTEM "xhtml-symbol.ent"> %HTMLsymbol; ]>
<document>
<header>
<attribute name="file" value="DN-20191003-skagen-topp-om-borsu.xml"/>
<attribute name="url" value="http://www.dn.no/bors/bors/usa/wall-street/skagen-topp-om-borsuroen-markedet-har-et-desperat-behov-for-avklaring/2-1-682554" frk="290 15 29 1905"/>
<attribute name="source" value="DN"/>
<attribute name="date" value="2019-10-03 14:32"/>
<attribute name="author" value="Jonas Solgård"/>
<attribute name="gender" value="M"/>
<attribute name="class1" value="bors,bors,usa,wall-street"/>
<attribute name="class2" value="Nyheter,Børs"/>
<attribute name="language" value="nob"/>
</header>
<body>
<div type="title" level="1">Skagen-topp om børsuroen: – Markedet har et desperat behov for avklaring</div>
<div type="ingress">Investeringsdirektør Alexandra Morris i Skagenfondene ser på den brede børsuroen med både bekymring og optimisme. Investeringsdirektør Alexandra Morris i Skagenfondene ser på den brede børsuroen med både bekymring og optimisme.</div>
<div type="author">Jonas Solgård</div>
<div type="date">2019-10-03 14:32</div>
<div type="caption">Alexandra Morris oppfordrer folk til å forholde seg rolig. Her avbildet utenfor Skagens kontorer i Stavanger sentrum. (Foto: Tommy Ellingsen) Investor Harald Espedal. Her fra detaljhandelskonferanse hos DNB i Bjørvika. (Foto: Andersen, Cicilie) Ingvild Borgen Gjerde i DNB Markets. (Foto: Gunnar Blöndal) </div>
<div type="text">
<p>Det ulmer i verdens børsmarkeder etter det analytikere beskriver som svake nøkkeltall fra USA. Den stadig eskalerende handelskonflikten mellom USA og Kina sender også investorene på flukt.</p>
<p>– Markedet har et desperat behov for avklaring. Akkurat nå er det mange ting som flyter samtidig og som også spiller inn i realøkonomien. Avklaringer om brexit, handelskrig, etc. vil hjelpe, men en vil nok også måtte se at økonomiene responderer før pulsen i markedet reduseres, sier Alexandra Morris i Skagenfondene.</p>
<p>De siste dagene har flere nøkkelindekser på Wall Street opplevd et nær historisk fall: industriindeksen Dow Jones har de to siste dagene falt med over 900 poeng til 26.078,62 poeng, mens den brede S&amp;P 500-indeksen har sin dårligste start på fjerde kvartal siden finanskrisen i 2008 og 2009.</p>
<p>I Asia var det også et bredt børsfall natt til torsdag, der blant annet Nikkei-indeksen i Japan og Australia-børsen er ned over to prosent. Oslo Børs fulgte også etter fra start torsdag morgen, og var ned litt over én prosent fire minutter etter åpning.</p>
<p>Oslo Børs hentet seg inn noe utover dagen, men gikk på en ny smell da det det kom dårligere nøkkeltall enn ventet fra den amerikanske tjenestesektoren. Hovedindeksen endte derfor torsdagen på 856,05 poeng, ned 1,34 prosent.</p></div></body></document>
