<?xml version="1.0" encoding="UTF-8"?>
<!DOCTYPE document SYSTEM "avis2.dtd" [<!ENTITY % HTMLsymbol SYSTEM "xhtml-symbol.ent"> %HTMLsymbol; ]>
<document>
<header>
<attribute name="file" value="DN-20191108-investor-jens-ulltve.xml"/>
<attribute name="url" value="http://www.dn.no/klima/jens-ulltveit-moe/norges-bank/oljefondet/investor-jens-ulltveit-moe-nar-alvoret-i-klimakrisen-nar-inn-til-en-konferanse-i-norges-bank-da-har-vi-kommet-langt/2-1-703468" frk="269 0 0 1841"/>
<attribute name="source" value="DN"/>
<attribute name="date" value="2019-11-08 18:55"/>
<attribute name="author" value="Åshild Langved"/>
<attribute name="gender" value="K"/>
<attribute name="class1" value="klima,jens-ulltveit-moe,norges-bank,oljefondet"/>
<attribute name="class2" value="Nyheter,Klima"/>
<attribute name="language" value="nob"/>
</header>
<body>
<div type="title" level="1">Investor Jens Ulltveit-Moe: – Når alvoret i klimakrisen når inn til en konferanse i Norges Bank, da har vi kommet langt</div>
<div type="ingress">Det er intet mindre enn «sensasjonelt» at klimakrisen tas like alvorlig i Norges Bank som hos miljøstiftelsen Zero, mener investor Jens Ulltveit-Moe. Det er intet mindre enn «sensasjonelt» at klimakrisen tas like alvorlig i Norges Bank som hos miljøstiftelsen Zero, mener investor Jens Ulltveit-Moe.</div>
<div type="author">Åshild Langved</div>
<div type="date">2019-11-08 18:55</div>
<div type="caption">Investor Jens Ulltveit-Moe mener Norges Bank er like på ballen som miljøaktivistene når det gjelder klimarisiko. Her sammen med visesentralbanksjef Egil Matsen (til høyre) og finansråd Hans Henrik Scheel. (Foto: Alle foto: Javad Parsa) Aps nestleder og finanspolitisk talskvinne, Hadia Tajik, var innom banken for første gang, fordi hun er interessert i temaet og ville høre mer. Talen til visesentralbanksjef Egil Matsen ligger klar. Tidligere toppbyråkrat Martin Skancke kommenterte talen til visesentralbanksjefen fredag. Skancke ledet blant annet regjeringens klimarisikoutvalg. (Foto: Javad Parsa) </div>
<div type="text">
<p>Fredag var det stinn brakke i lokalene til Norges Bank da visesentralbanksjef Egil Matsen snakket om klimarisiko.</p>
<p>Blant annet var både Ap-nestleder Hadia Tajik og eks-finansminister Kristin Halvorsen på plass. Det var også investor og eier av Umoe-gruppen, Jens Ulltveit-Moe. Han har selv investert i vindkraft og solenergi, og er en av landets mest klimaengasjerte investorer.</p>
<p>– Det er helt sensasjonelt det som skjedde nå i dag, sier Ulltveit-Moe.</p>
<p>– Hvorfor er det sensasjonelt?</p>
<p>– Jo, for klimaaktivistene ligger langt foran folkemeningen og den generelle elitemeningen. Nå kommer eliten etter. Det var det som skjedde her. Finansmarkedene kommer etter med en tørr språkdrakt, men budskapet er like voldsomt. Det reduserer risikoen i Oljefondet, og bidrar til å redde verden, svarer Ulltveit-Moe.</p></div></body></document>
