<?xml version="1.0" encoding="UTF-8"?>
<!DOCTYPE document SYSTEM "avis2.dtd" [<!ENTITY % HTMLsymbol SYSTEM "xhtml-symbol.ent"> %HTMLsymbol; ]>
<document>
<header>
<attribute name="file" value="DA-20190102-weng-forstuet-tommel.xml"/>
<attribute name="url" value="http://www.dagsavisen.no/sport/weng-forstuet-tommelen-fortsetter-tour-de-ski-1.1255077" frk="325 7 14 1910"/>
<attribute name="source" value="DA"/>
<attribute name="date" value="2019-01-02 20:47"/>
<attribute name="author" value="NTB"/>
<attribute name="gender" value="U"/>
<attribute name="class1" value="sport"/>
<attribute name="class2" value=""/>
<attribute name="language" value="nob"/>
</header>
<body>
<div type="title" level="1">Weng forstuet tommelen – fortsetter Tour de Ski</div>
<div type="ingress">Heidi Weng forstuet tommelen etter fallet i tirsdagens sprintkvartfinale i Tour de Ski, men fortsetter likevel touren i Oberstdorf onsdag.</div>
<div type="author"></div>
<div type="date"></div>
<div type="caption"><p>Heidi Weng falt og forstuet tommelen under sprinten i Val Müstair tirsdag.</p></div>
<div type="text">
<p>– Heidi har forstuet høyre tommelfinger, men står på videre med konkurransene, bekrefter landslagslege Øystein Andersen sent tirsdag kveld.</p>
<p>Weng gikk i bakken og fikk en skade i den ene tommelen under tirsdagens sprintkvartfinale, og var fortvilet da hun snakket med mediene i målområdet.</p>
<p>– Jeg får håpe bare at den ikke er brukket, sa Weng om den vonde tommelen.</p>
<p>Det var den heldigvis ikke, og dermed er hun klar for onsdagens 10 kilometer.</p></div>
<div type="title" level="3">Vondt</div>
<div type="text">
<p>– Det er vondt, men det skal være mulig å gå videre med denne skaden selv om tommelen er vond. Hvis den er forstuet, så skal vi prøve å mekke den til, sa Andersen til mediene etter fallet.</p>
<p>– En forstuing gjør at det er vondt ganske lenge, selv om man er rimelig raskt tilbake i trening. Er det vondt uten en verre skade er det greit, men det blir en ny vurdering i kveld. Vi får se om vi må fram med en Reodor Felgen-teip. Hvis ikke det er noe leddbåndbrudd, så er det smertene som er verst, sa landslagslegen videre tirsdag.</p>
<p>Weng ligger på 13.-plass i sammendraget etter tre etapper i touren. Hun har 1.35,9 sekunder opp til ledende Jessica Diggins.</p></div>
<div type="title" level="3">Falla-exit</div>
<div type="text">
<p>I motsetning til Weng, velger Maiken Caspersen Falla å stå av Tour de Ski én etappe før planlagt. 28-åringen skulle i utgangspunktet stille til start på onsdagens 10 kilometer i klassisk stil i tyske Oberstdorf. Deretter var planen at hun skulle reise hjem.</p>
<p>– Maiken skulle etter planen reise hjem etter løpet i Oberstdorf i dag, men stå over konkurransen for å spare luftveiene, sier landslagslege Øystein Andersen.</p>
<p>Falla ble nummer fem på tirsdagens sprint i Val Müstair og lå på 19.-plass i Tour-sammendraget.</p>
<p>(NTB)</p></div></body></document>
