<?xml version="1.0" encoding="UTF-8"?>
<!DOCTYPE document SYSTEM "avis2.dtd" [<!ENTITY % HTMLsymbol SYSTEM "xhtml-symbol.ent"> %HTMLsymbol; ]>
<document>
<header>
<attribute name="file" value="FV-20190329-kjemper-for-a-heve-b.xml"/>
<attribute name="url" value="http://www.fvn.no/nyheter/lokalt/i/OpkW7b/Kjemper-for-a-heve-boligkjop-etter-ras--Hver-gang-det-regner-blir-jeg-redd" frk="60 0 0 393 %%"/>
<attribute name="source" value="FV"/>
<attribute name="date" value="2019-03-29 13:40"/>
<attribute name="author" value=""/>
<attribute name="gender" value="U"/>
<attribute name="class1" value="nyheter,lokalt"/>
<attribute name="class2" value="nyheter,lokalt"/>
<attribute name="language" value="nob"/>
</header>
<body>
<div type="title" level="1">Kjemper for å heve boligkjøp etter ras: – Hver gang det regner blir jeg redd</div>
<div type="ingress">Etter halvannet år har Nihren Moshe Dawood fortsatt ikke flyttet tilbake til huset hun bodde i da muren utenfor raste sammen. Denne uka møtte hun boligselgeren Sør-Hus i retten.</div>
<div type="author"></div>
<div type="date"></div>
<div type="caption"><p>Nihren Moshe Dawood (t.v.) og advokatfullmektig Heidi Reisvang i Kristiansand tingrett onsdag. FOTO: Eivind Kristensen</p></div>
</body></document>
