<?xml version="1.0" encoding="UTF-8"?>
<!DOCTYPE document SYSTEM "avis2.dtd" [<!ENTITY % HTMLsymbol SYSTEM "xhtml-symbol.ent"> %HTMLsymbol; ]>
<document>
<header>
<attribute name="file" value="SA-20190226-god-svommeteknikk-er.xml"/>
<attribute name="url" value="http://www.aftenbladet.no/100Sport/sprek/God-svommeteknikk-er-avgjorende-i-triatlon-Dette-er-triksene-268699b.html" frk="73 0 0 448 %%"/>
<attribute name="source" value="SA"/>
<attribute name="date" value="2019-02-26 09:05"/>
<attribute name="author" value=""/>
<attribute name="gender" value="U"/>
<attribute name="class1" value="sport, sprek"/>
<attribute name="class2" value="triatlon,trening,helse"/>
<attribute name="language" value="nob"/>
</header>
<body>
<div type="title" level="1">God svømmeteknikk er avgjørende i triatlon. Dette er triksene.</div>
<div type="ingress">– Skal du bli god i triatlon, nytter det ikke med brystsvømming. Med god crawleteknikk kan du halvere svømmetiden, sier ekspert.</div>
<div type="author"></div>
<div type="date"></div>
<div type="caption"><p>BITT AV BASILLEN: Triatlonutøver Kjetil Pedersen regner seg som mosjonist selv om han trener nesten hver dag. Det er ikke mange år siden han begynte å trene, men det gikk ikke lang tid før han begynte å delta i triatlon. Pål Christensen</p></div>
</body></document>
